mypvdevices/ChannelConfig.py
mypvdevices/Dataprocessor.py
mypvdevices/DcsConnection.py
mypvdevices/DeviceAcThor.py
mypvdevices/DeviceConfigurable.py
mypvdevices/DeviceDcElwa.py
mypvdevices/DeviceDiscoverer.py
mypvdevices/DummyDevice.py
mypvdevices/DummyTcpDevice.py
mypvdevices/EastronMeter.py
mypvdevices/ElwaSc20.py
mypvdevices/GeneralDevice.py
mypvdevices/ModbusConnection.py
mypvdevices/ModbusDevice.py
mypvdevices/ModbusRtuDevice.py
mypvdevices/ModbusTcpDevice.py
mypvdevices/MyDevice.py
mypvdevices/Powermeter.py
mypvdevices/SensorS5140.py
mypvdevices/SerialDevice.py
mypvdevices/ServerConnection.py
mypvdevices/SetupMapping.py
mypvdevices/__init__.py
my_pv_lib-1.2202.2.dist-info/LICENSE
my_pv_lib-1.2202.2.dist-info/METADATA
my_pv_lib-1.2202.2.dist-info/WHEEL
my_pv_lib-1.2202.2.dist-info/top_level.txt
my_pv_lib-1.2202.2.dist-info/RECORD
