Metadata-Version: 2.1
Name: my-pv-lib
Version: 1.2202.2
Summary: my-PV python library
Home-page: https://www.my-pv.com/de/info/downloads
Author: my-PV GmbH
Author-email: info@my-pv.com
License: UNKNOWN
Platform: UNKNOWN
Classifier: Programming Language :: Python :: 3
Classifier: License :: OSI Approved :: MIT License
Classifier: Operating System :: OS Independent
License-File: LICENSE
